<?xml version="1.0"?>
<catalog>
  <produto>
     <nome>Creme de Ninho</nome>
     <foto>http://uploaddeimagens.com.br/images/001/243/647/original/cremeninho.png?1515523374</foto>
     <preco>1,00</preco>
     <precoComDesconto>0,75</precoComDesconto>
  </produto>
  <produto>
     <nome>Abacaxi</nome>
     <foto>http://uploaddeimagens.com.br/images/001/253/463/full/abacaxi.jpg?1516204609</foto>
     <preco>1,00</preco>
     <precoComDesconto>0,75</precoComDesconto>
  </produto>
  <produto>
     <nome>Côco comum ou queimado</nome>
     <foto>http://uploaddeimagens.com.br/images/001/256/102/full/2cocos.png?1516371981</foto>
     <preco>1,00</preco>
     <precoComDesconto>0,85</precoComDesconto>
  </produto>
  
  <produto>
     <nome>Nozes</nome>
     <foto>http://uploaddeimagens.com.br/images/001/243/565/original/IMG-20180109-WA0016.jpg?1515519928</foto>
     <preco>1,30</preco>
     <precoComDesconto>1,10</precoComDesconto>
  </produto>
  
  <produto>
     <nome>Brigadeiro ao leite ou branco</nome>
     <foto>http://uploaddeimagens.com.br/images/001/243/568/original/IMG-20180109-WA0024.jpg?1515519971</foto>
     <preco>1,50</preco>
     <precoComDesconto>1,30</precoComDesconto>
  </produto>
  
  
  <produto>
     <nome>Creme de ninho recheado</nome>
     <foto>http://uploaddeimagens.com.br/images/001/253/464/full/ninho.jpg?1516204623</foto>
     <preco>1,50</preco>
     <precoComDesconto>1,20</precoComDesconto>
  </produto>
  
  
  <produto>
     <nome>Uva</nome>
     <foto>http://uploaddeimagens.com.br/images/001/243/570/original/IMG-20180109-WA0027.jpg?1515519999</foto>
     <preco>2,50</preco>
     <precoComDesconto>1,50</precoComDesconto>
  </produto>
  
</catalog>
